icw_lib-2.0.1.dist-info/DESCRIPTION.rst
icw_lib-2.0.1.dist-info/METADATA
icw_lib-2.0.1.dist-info/RECORD
icw_lib-2.0.1.dist-info/WHEEL
icw_lib-2.0.1.dist-info/metadata.json
icw_lib-2.0.1.dist-info/top_level.txt
lib/Crawler.py
lib/Downloader.py
lib/Validator.py
lib/__init__.py
