Metadata-Version: 2.0
Name: icw-lib
Version: 2.0.1
Summary: Instagram data crawler.
Home-page: https://github.com/Haneawa/icw-lib
Author: Alberto Ocaranza
Author-email: haneawa.contact@gmail.com
License: UNKNOWN
Platform: UNKNOWN
Classifier: Programming Language :: Python :: 3
Classifier: License :: OSI Approved :: MIT License
Classifier: Operating System :: OS Independent
